loopflow/LOOPFLOW.md
loopflow/STYLE.md
loopflow/__init__.py
loopflow/init_check.py
loopflow/publish.py
loopflow/lf/__init__.py
loopflow/lf/branch_names.py
loopflow/lf/cli.py
loopflow/lf/config.py
loopflow/lf/context.py
loopflow/lf/deps.py
loopflow/lf/design.py
loopflow/lf/directions.py
loopflow/lf/execution.py
loopflow/lf/files.py
loopflow/lf/flow.py
loopflow/lf/flows.py
loopflow/lf/frontmatter.py
loopflow/lf/git.py
loopflow/lf/launcher.py
loopflow/lf/logging.py
loopflow/lf/messages.py
loopflow/lf/naming.py
loopflow/lf/output.py
loopflow/lf/roadmap.py
loopflow/lf/skills.py
loopflow/lf/step.py
loopflow/lf/tokens.py
loopflow/lf/wave.py
loopflow/lf/worktrees.py
loopflow/lf/builtins/__init__.py
loopflow/lf/builtins/commit_message.txt
loopflow/lf/builtins/pr_message.txt
loopflow/lf/builtins/prompts.py
loopflow/lf/builtins/release_notes.txt
loopflow/lf/builtins/summarize.txt
loopflow/lf/builtins/directions/roles/ceo.md
loopflow/lf/builtins/directions/roles/designer.md
loopflow/lf/builtins/directions/roles/infra-engineer.md
loopflow/lf/builtins/directions/roles/product-engineer.md
loopflow/lf/builtins/directions/values/craft.md
loopflow/lf/builtins/directions/values/flow.md
loopflow/lf/builtins/directions/values/scale.md
loopflow/lf/builtins/flows/README.md
loopflow/lf/builtins/flows/code/design-and-ship.yaml
loopflow/lf/builtins/flows/code/grind.yaml
loopflow/lf/builtins/flows/code/incident.yaml
loopflow/lf/builtins/flows/code/pair.yaml
loopflow/lf/builtins/flows/code/ship-roadmap.yaml
loopflow/lf/builtins/flows/code/ship.yaml
loopflow/lf/builtins/flows/code/start.yaml
loopflow/lf/builtins/flows/plan/publish.yaml
loopflow/lf/builtins/flows/plan/research.yaml
loopflow/lf/builtins/flows/plan/roadmap-expand.yaml
loopflow/lf/builtins/flows/plan/roadmap-polish.yaml
loopflow/lf/builtins/flows/plan/roadmap-reduce.yaml
loopflow/lf/builtins/steps/code/compress.md
loopflow/lf/builtins/steps/code/debug.md
loopflow/lf/builtins/steps/code/gate.md
loopflow-0.7.2.dist-info/METADATA
loopflow-0.7.2.dist-info/WHEEL
loopflow-0.7.2.dist-info/entry_points.txt
loopflow-0.7.2.dist-info/RECORD
