Metadata-Version: 2.4
Name: loopflow
Version: 0.7.2
Summary: Run LLM coding agents from reusable prompt files
Project-URL: Homepage, https://loopflowstudio.github.io/loopflow/
Project-URL: Repository, https://github.com/loopflowstudio/loopflow
Project-URL: Documentation, https://loopflowstudio.github.io/loopflow/
Project-URL: Issues, https://github.com/loopflowstudio/loopflow/issues
Project-URL: Changelog, https://github.com/loopflowstudio/loopflow/releases
Author: Jack
License-Expression: MIT
Keywords: agents,ai,automation,claude,cli,codex,coding,gemini,llm,prompts,workflow
Classifier: Development Status :: 3 - Alpha
Classifier: Environment :: Console
Classifier: Intended Audience :: Developers
Classifier: License :: OSI Approved :: MIT License
Classifier: Operating System :: MacOS
Classifier: Programming Language :: Python :: 3
Classifier: Programming Language :: Python :: 3.10
Classifier: Programming Language :: Python :: 3.11
Classifier: Programming Language :: Python :: 3.12
Classifier: Topic :: Software Development
Classifier: Typing :: Typed
Requires-Python: >=3.10
Requires-Dist: croniter>=2.0
Requires-Dist: fastapi>=0.115.0
Requires-Dist: grpcio-tools>=1.60.0
Requires-Dist: grpcio>=1.60.0
Requires-Dist: pathspec>=0.11.0
Requires-Dist: protobuf>=4.25.0
Requires-Dist: pydantic>=2.12.5
Requires-Dist: pyyaml>=6.0
Requires-Dist: tiktoken>=0.7.0
Requires-Dist: typer>=0.9.0
Requires-Dist: uvicorn>=0.34.0
Provides-Extra: dev
Requires-Dist: pytest>=7.0.0; extra == 'dev'
